{
  "names": [
    "Bedabin Nomad Fighter"
  ],
  "hitpoints": 500,
  "attackAnim": -1,
  "defenceAnim": -1,
  "deathAnim": -1,
  "deathDelay": 3,
  "respawnDelay": 79,
  "maxHit": 1,
  "attackStyle": "MELEE",
  "attackGfx": -1,
  "attackProjectile": -1,
  "agressivenessType": "PASSIVE",
  "attackBonus": "SLASH_ATT",
  "combatLevels": {
    "ATTACK": 40,
    "RANGE": 0,
    "STRENGTH": 50,
    "DEFENSE": 60,
    "MAGE": 0
  },
  "aggroDistance": -1,
  "deAggroDistance": -1,
  "maxDistFromSpawn": -1,
  "attackRange": -1
}