{
  "ids": [
    54,
    4673,
    4674,
    4675,
    4676
  ],
  "hitpoints": 1900,
  "attackAnim": 12252,
  "defenceAnim": 12251,
  "deathAnim": 12250,
  "deathDelay": 3,
  "respawnDelay": 119,
  "maxHit": 214,
  "attackStyle": "SPECIAL2",
  "attackGfx": -1,
  "attackProjectile": -1,
  "agressivenessType": "AGGRESSIVE",
  "attackBonus": "SLASH_ATT",
  "combatLevels": {
    "ATTACK": 200,
    "RANGE": 1,
    "STRENGTH": 200,
    "DEFENSE": 200,
    "MAGE": 100
  },
  "aggroDistance": -1,
  "deAggroDistance": -1,
  "maxDistFromSpawn": -1,
  "attackRange": -1
}