{
  "ids": [
    8,
    2674,
    2696,
    5926,
    5927,
    5928,
    5929
  ],
  "hitpoints": 160,
  "attackAnim": -1,
  "defenceAnim": -1,
  "deathAnim": -1,
  "deathDelay": 3,
  "respawnDelay": 119,
  "maxHit": 20,
  "attackStyle": "MELEE",
  "attackGfx": -1,
  "attackProjectile": -1,
  "agressivenessType": "PASSIVE",
  "combatLevels": {
    "ATTACK": 14,
    "RANGE": 1,
    "STRENGTH": 13,
    "DEFENSE": 12,
    "MAGE": 1
  },
  "aggroDistance": -1,
  "deAggroDistance": -1,
  "maxDistFromSpawn": -1,
  "attackRange": -1
}