{
  "names": [
    "Giant spider"
  ],
  "tables": [
    {
      "chance": 5247.0,
      "outOf": 25000.0,
      "dropOne": false,
      "drops": [
        {
          "id": 526,
          "min": 1,
          "max": 1
        }
      ]
    },
    {
      "chance": 5247.0,
      "outOf": 25000.0,
      "dropOne": false,
      "drops": [
        {
          "id": 995,
          "min": 1,
          "max": 1
        }
      ]
    },
    {
      "chance": 5247.0,
      "outOf": 25000.0,
      "dropOne": false,
      "drops": [
        {
          "id": 1965,
          "min": 1,
          "max": 1
        }
      ]
    },
    {
      "chance": 5247.0,
      "outOf": 25000.0,
      "dropOne": false,
      "drops": [
        {
          "id": 2307,
          "min": 1,
          "max": 1
        }
      ]
    },
    {
      "chance": 583.0,
      "outOf": 25000.0,
      "dropOne": false,
      "drops": [
        {
          "id": 554,
          "min": 6,
          "max": 6
        }
      ]
    },
    {
      "chance": 583.0,
      "outOf": 25000.0,
      "dropOne": false,
      "drops": [
        {
          "id": 556,
          "min": 1,
          "max": 4
        }
      ]
    },
    {
      "chance": 583.0,
      "outOf": 25000.0,
      "dropOne": false,
      "drops": [
        {
          "id": 557,
          "min": 4,
          "max": 4
        }
      ]
    },
    {
      "chance": 583.0,
      "outOf": 25000.0,
      "dropOne": false,
      "drops": [
        {
          "id": 877,
          "min": 8,
          "max": 8
        }
      ]
    },
    {
      "chance": 583.0,
      "outOf": 25000.0,
      "dropOne": false,
      "drops": [
        {
          "id": 882,
          "min": 4,
          "max": 8
        }
      ]
    },
    {
      "chance": 583.0,
      "outOf": 25000.0,
      "dropOne": false,
      "drops": [
        {
          "id": 1440,
          "min": 1,
          "max": 1
        }
      ]
    },
    {
      "chance": 233.0,
      "outOf": 100000.0,
      "dropOne": false,
      "drops": [
        {
          "id": 229,
          "min": 1,
          "max": 1
        }
      ]
    },
    {
      "chance": 233.0,
      "outOf": 100000.0,
      "dropOne": false,
      "drops": [
        {
          "id": 559,
          "min": 7,
          "max": 7
        }
      ]
    },
    {
      "chance": 233.0,
      "outOf": 100000.0,
      "dropOne": false,
      "drops": [
        {
          "id": 839,
          "min": 1,
          "max": 1
        }
      ]
    },
    {
      "chance": 233.0,
      "outOf": 100000.0,
      "dropOne": false,
      "drops": [
        {
          "id": 1009,
          "min": 1,
          "max": 1
        }
      ]
    },
    {
      "chance": 233.0,
      "outOf": 100000.0,
      "dropOne": false,
      "drops": [
        {
          "id": 1381,
          "min": 1,
          "max": 1
        }
      ]
    },
    {
      "chance": 233.0,
      "outOf": 100000.0,
      "dropOne": false,
      "drops": [
        {
          "id": 1438,
          "min": 1,
          "max": 1
        }
      ]
    },
    {
      "chance": 233.0,
      "outOf": 100000.0,
      "dropOne": false,
      "drops": [
        {
          "id": 1955,
          "min": 2,
          "max": 2
        }
      ]
    },
    {
      "chance": 233.0,
      "outOf": 100000.0,
      "dropOne": false,
      "drops": [
        {
          "id": 19830,
          "min": 1,
          "max": 1
        }
      ]
    },
    {
      "chance": 93.0,
      "outOf": 100000.0,
      "dropOne": false,
      "drops": [
        {
          "id": 1189,
          "min": 1,
          "max": 1
        }
      ]
    },
    {
      "chance": 93.0,
      "outOf": 100000.0,
      "dropOne": false,
      "drops": [
        {
          "id": 1444,
          "min": 1,
          "max": 1
        }
      ]
    }
  ]
}