{
  "names": [
    "Mithril dragon"
  ],
  "tables": [
    {
      "chance": 0.0,
      "outOf": 0.0,
      "dropOne": false,
      "drops": [
        {
          "id": 536,
          "min": 1,
          "max": 1
        }
      ]
    },
    {
      "chance": 0.0,
      "outOf": 0.0,
      "dropOne": false,
      "drops": [
        {
          "id": 2359,
          "min": 3,
          "max": 3
        }
      ]
    },
    {
      "chance": 18.0,
      "outOf": 128.0,
      "dropOne": false,
      "drops": [
        {
          "id": 565,
          "min": 27,
          "max": 27
        }
      ]
    },
    {
      "chance": 17.0,
      "outOf": 128.0,
      "dropOne": false,
      "drops": [
        {
          "id": 995,
          "min": 600,
          "max": 600
        }
      ]
    },
    {
      "chance": 14.0,
      "outOf": 128.0,
      "dropOne": false,
      "drops": [
        {
          "id": 830,
          "min": 8,
          "max": 8
        }
      ]
    },
    {
      "chance": 12.0,
      "outOf": 128.0,
      "dropOne": false,
      "drops": [
        {
          "id": 1373,
          "min": 1,
          "max": 1
        }
      ]
    },
    {
      "chance": 7.0,
      "outOf": 128.0,
      "dropOne": false,
      "drops": [
        {
          "id": 817,
          "min": 14,
          "max": 14
        }
      ]
    },
    {
      "chance": 7.0,
      "outOf": 128.0,
      "dropOne": false,
      "drops": [
        {
          "id": 995,
          "min": 876,
          "max": 876
        }
      ]
    },
    {
      "chance": 6.0,
      "outOf": 128.0,
      "dropOne": false,
      "drops": [
        {
          "id": 9144,
          "min": 10,
          "max": 21
        }
      ]
    },
    {
      "chance": 6.0,
      "outOf": 128.0,
      "dropOne": false,
      "drops": [
        {
          "id": 385,
          "min": 1,
          "max": 1
        }
      ]
    },
    {
      "chance": 5.0,
      "outOf": 128.0,
      "dropOne": false,
      "drops": [
        {
          "id": 566,
          "min": 10,
          "max": 10
        }
      ]
    },
    {
      "chance": 4.0,
      "outOf": 128.0,
      "dropOne": false,
      "rollTable": "rdt_gem"
    },
    {
      "chance": 3.0,
      "outOf": 128.0,
      "dropOne": false,
      "drops": [
        {
          "id": 868,
          "min": 8,
          "max": 8
        }
      ]
    },
    {
      "chance": 3.0,
      "outOf": 128.0,
      "dropOne": false,
      "drops": [
        {
          "id": 1432,
          "min": 1,
          "max": 1
        }
      ]
    },
    {
      "chance": 3.0,
      "outOf": 128.0,
      "dropOne": false,
      "drops": [
        {
          "id": 892,
          "min": 8,
          "max": 8
        }
      ]
    },
    {
      "chance": 3.0,
      "outOf": 128.0,
      "dropOne": false,
      "drops": [
        {
          "id": 11338,
          "min": 1,
          "max": 1
        }
      ]
    },
    {
      "chance": 3.0,
      "outOf": 128.0,
      "dropOne": false,
      "drops": [
        {
          "id": 2363,
          "min": 2,
          "max": 2
        }
      ]
    },
    {
      "chance": 2.0,
      "outOf": 128.0,
      "dropOne": false,
      "drops": [
        {
          "id": 1247,
          "min": 1,
          "max": 1
        }
      ]
    },
    {
      "chance": 2.0,
      "outOf": 128.0,
      "dropOne": false,
      "drops": [
        {
          "id": 11465,
          "min": 1,
          "max": 1
        }
      ]
    },
    {
      "chance": 2.0,
      "outOf": 128.0,
      "dropOne": false,
      "drops": [
        {
          "id": 385,
          "min": 6,
          "max": 6
        }
      ]
    },
    {
      "chance": 2.0,
      "outOf": 128.0,
      "dropOne": false,
      "drops": [
        {
          "id": 11469,
          "min": 1,
          "max": 1
        }
      ]
    },
    {
      "chance": 2.0,
      "outOf": 128.0,
      "dropOne": false,
      "drops": [
        {
          "id": 11497,
          "min": 1,
          "max": 1
        }
      ]
    },
    {
      "chance": 2.0,
      "outOf": 128.0,
      "dropOne": false,
      "drops": [
        {
          "id": 11485,
          "min": 1,
          "max": 1
        }
      ]
    },
    {
      "chance": 2.0,
      "outOf": 128.0,
      "dropOne": false,
      "drops": [
        {
          "id": 11341,
          "min": 1,
          "max": 1
        }
      ]
    },
    {
      "chance": 1.0,
      "outOf": 128.0,
      "dropOne": false,
      "drops": [
        {
          "id": 1163,
          "min": 1,
          "max": 1
        }
      ]
    },
    {
      "chance": 1.0,
      "outOf": 128.0,
      "dropOne": false,
      "rollTable": "rdt_standard"
    },
    {
      "chance": 1.0,
      "outOf": 10000.0,
      "dropOne": false,
      "drops": [
        {
          "id": 11286,
          "min": 1,
          "max": 1
        }
      ]
    },
    {
      "chance": 1.0,
      "outOf": 32768.0,
      "dropOne": false,
      "drops": [
        {
          "id": 11335,
          "min": 1,
          "max": 1
        }
      ]
    }
  ]
}