{
  "names": [
    "Ork"
  ],
  "tables": [
    {
      "chance": 0.0,
      "outOf": 0.0,
      "dropOne": false,
      "drops": [
        {
          "id": 526,
          "min": 1,
          "max": 1
        }
      ]
    },
    {
      "chance": 8.0,
      "outOf": 128.0,
      "dropOne": false,
      "drops": [
        {
          "id": 995,
          "min": 10,
          "max": 10
        }
      ]
    },
    {
      "chance": 5.0,
      "outOf": 128.0,
      "dropOne": false,
      "drops": [
        {
          "id": 1307,
          "min": 1,
          "max": 1
        }
      ]
    },
    {
      "chance": 5.0,
      "outOf": 128.0,
      "dropOne": false,
      "drops": [
        {
          "id": 1375,
          "min": 1,
          "max": 1
        }
      ]
    },
    {
      "chance": 5.0,
      "outOf": 128.0,
      "dropOne": false,
      "drops": [
        {
          "id": 806,
          "min": 2,
          "max": 2
        }
      ]
    },
    {
      "chance": 5.0,
      "outOf": 128.0,
      "dropOne": false,
      "drops": [
        {
          "id": 3190,
          "min": 1,
          "max": 1
        }
      ]
    },
    {
      "chance": 5.0,
      "outOf": 128.0,
      "dropOne": false,
      "drops": [
        {
          "id": 1321,
          "min": 1,
          "max": 1
        }
      ]
    },
    {
      "chance": 5.0,
      "outOf": 128.0,
      "dropOne": false,
      "drops": [
        {
          "id": 1337,
          "min": 1,
          "max": 1
        }
      ]
    },
    {
      "chance": 5.0,
      "outOf": 128.0,
      "dropOne": false,
      "drops": [
        {
          "id": 807,
          "min": 2,
          "max": 2
        }
      ]
    },
    {
      "chance": 5.0,
      "outOf": 128.0,
      "dropOne": false,
      "drops": [
        {
          "id": 1293,
          "min": 1,
          "max": 1
        }
      ]
    },
    {
      "chance": 5.0,
      "outOf": 128.0,
      "dropOne": false,
      "drops": [
        {
          "id": 1420,
          "min": 1,
          "max": 1
        }
      ]
    },
    {
      "chance": 5.0,
      "outOf": 128.0,
      "dropOne": false,
      "drops": [
        {
          "id": 1323,
          "min": 1,
          "max": 1
        }
      ]
    },
    {
      "chance": 5.0,
      "outOf": 128.0,
      "dropOne": false,
      "drops": [
        {
          "id": 1353,
          "min": 1,
          "max": 1
        }
      ]
    },
    {
      "chance": 5.0,
      "outOf": 128.0,
      "dropOne": false,
      "drops": [
        {
          "id": 1207,
          "min": 1,
          "max": 1
        }
      ]
    },
    {
      "chance": 5.0,
      "outOf": 128.0,
      "dropOne": false,
      "drops": [
        {
          "id": 1424,
          "min": 1,
          "max": 1
        }
      ]
    },
    {
      "chance": 5.0,
      "outOf": 128.0,
      "dropOne": false,
      "drops": [
        {
          "id": 1139,
          "min": 1,
          "max": 1
        }
      ]
    },
    {
      "chance": 5.0,
      "outOf": 128.0,
      "dropOne": false,
      "drops": [
        {
          "id": 1155,
          "min": 1,
          "max": 1
        }
      ]
    },
    {
      "chance": 5.0,
      "outOf": 128.0,
      "dropOne": false,
      "drops": [
        {
          "id": 1075,
          "min": 1,
          "max": 1
        }
      ]
    },
    {
      "chance": 5.0,
      "outOf": 128.0,
      "dropOne": false,
      "drops": [
        {
          "id": 1101,
          "min": 1,
          "max": 1
        }
      ]
    },
    {
      "chance": 5.0,
      "outOf": 128.0,
      "dropOne": false,
      "drops": [
        {
          "id": 1141,
          "min": 1,
          "max": 1
        }
      ]
    },
    {
      "chance": 5.0,
      "outOf": 128.0,
      "dropOne": false,
      "drops": [
        {
          "id": 995,
          "min": 5,
          "max": 5
        }
      ]
    },
    {
      "chance": 5.0,
      "outOf": 128.0,
      "dropOne": false,
      "drops": [
        {
          "id": 995,
          "min": 8,
          "max": 8
        }
      ]
    },
    {
      "chance": 5.0,
      "outOf": 128.0,
      "dropOne": false,
      "drops": [
        {
          "id": 995,
          "min": 12,
          "max": 12
        }
      ]
    },
    {
      "chance": 5.0,
      "outOf": 128.0,
      "dropOne": false,
      "drops": [
        {
          "id": 995,
          "min": 23,
          "max": 23
        }
      ]
    },
    {
      "chance": 5.0,
      "outOf": 128.0,
      "dropOne": false,
      "drops": [
        {
          "id": 946,
          "min": 1,
          "max": 1
        }
      ]
    },
    {
      "chance": 4.0,
      "outOf": 128.0,
      "dropOne": false,
      "drops": [
        {
          "id": 1239,
          "min": 1,
          "max": 1
        }
      ]
    },
    {
      "chance": 1.0,
      "outOf": 128.0,
      "dropOne": false,
      "drops": [
        {
          "id": 1321,
          "min": 1,
          "max": 1
        }
      ]
    }
  ]
}