{
  "names": [
    "Skeleton fremennik"
  ],
  "tables": [
    {
      "chance": 0.0,
      "outOf": 0.0,
      "dropOne": false,
      "drops": [
        {
          "id": 526,
          "min": 1,
          "max": 1
        }
      ]
    },
    {
      "chance": 9.0,
      "outOf": 20.0,
      "dropOne": false,
      "drops": [
        {
          "id": 995,
          "min": 20,
          "max": 185
        }
      ]
    },
    {
      "chance": 9.0,
      "outOf": 20.0,
      "dropOne": false,
      "drops": [
        {
          "id": 1361,
          "min": 1,
          "max": 1
        }
      ]
    },
    {
      "chance": 1.0,
      "outOf": 17500.0,
      "dropOne": false,
      "drops": [
        {
          "id": 526,
          "min": 1,
          "max": 1
        }
      ]
    },
    {
      "chance": 1.0,
      "outOf": 17500.0,
      "dropOne": false,
      "drops": [
        {
          "id": 555,
          "min": 20,
          "max": 20
        }
      ]
    },
    {
      "chance": 1.0,
      "outOf": 17500.0,
      "dropOne": false,
      "drops": [
        {
          "id": 556,
          "min": 60,
          "max": 60
        }
      ]
    },
    {
      "chance": 1.0,
      "outOf": 17500.0,
      "dropOne": false,
      "drops": [
        {
          "id": 562,
          "min": 9,
          "max": 9
        }
      ]
    },
    {
      "chance": 1.0,
      "outOf": 17500.0,
      "dropOne": false,
      "drops": [
        {
          "id": 563,
          "min": 2,
          "max": 2
        }
      ]
    },
    {
      "chance": 1.0,
      "outOf": 17500.0,
      "dropOne": false,
      "drops": [
        {
          "id": 564,
          "min": 4,
          "max": 4
        }
      ]
    },
    {
      "chance": 1.0,
      "outOf": 17500.0,
      "dropOne": false,
      "drops": [
        {
          "id": 888,
          "min": 8,
          "max": 8
        }
      ]
    },
    {
      "chance": 1.0,
      "outOf": 17500.0,
      "dropOne": false,
      "drops": [
        {
          "id": 1265,
          "min": 1,
          "max": 1
        }
      ]
    },
    {
      "chance": 1.0,
      "outOf": 17500.0,
      "dropOne": false,
      "drops": [
        {
          "id": 1281,
          "min": 1,
          "max": 1
        }
      ]
    },
    {
      "chance": 1.0,
      "outOf": 17500.0,
      "dropOne": false,
      "drops": [
        {
          "id": 1329,
          "min": 1,
          "max": 1
        }
      ]
    },
    {
      "chance": 1.0,
      "outOf": 17500.0,
      "dropOne": false,
      "drops": [
        {
          "id": 2359,
          "min": 1,
          "max": 1
        }
      ]
    },
    {
      "chance": 1.0,
      "outOf": 17500.0,
      "dropOne": false,
      "drops": [
        {
          "id": 5100,
          "min": 1,
          "max": 1
        }
      ]
    },
    {
      "chance": 1.0,
      "outOf": 17500.0,
      "dropOne": false,
      "drops": [
        {
          "id": 5104,
          "min": 1,
          "max": 1
        }
      ]
    },
    {
      "chance": 1.0,
      "outOf": 17500.0,
      "dropOne": false,
      "drops": [
        {
          "id": 5105,
          "min": 1,
          "max": 1
        }
      ]
    },
    {
      "chance": 1.0,
      "outOf": 17500.0,
      "dropOne": false,
      "drops": [
        {
          "id": 5106,
          "min": 1,
          "max": 1
        }
      ]
    },
    {
      "chance": 1.0,
      "outOf": 17500.0,
      "dropOne": false,
      "drops": [
        {
          "id": 5280,
          "min": 1,
          "max": 1
        }
      ]
    },
    {
      "chance": 1.0,
      "outOf": 17500.0,
      "dropOne": false,
      "drops": [
        {
          "id": 5282,
          "min": 1,
          "max": 1
        }
      ]
    },
    {
      "chance": 1.0,
      "outOf": 17500.0,
      "dropOne": false,
      "drops": [
        {
          "id": 5291,
          "min": 1,
          "max": 1
        }
      ]
    },
    {
      "chance": 1.0,
      "outOf": 17500.0,
      "dropOne": false,
      "drops": [
        {
          "id": 5292,
          "min": 1,
          "max": 1
        }
      ]
    },
    {
      "chance": 1.0,
      "outOf": 17500.0,
      "dropOne": false,
      "drops": [
        {
          "id": 5293,
          "min": 1,
          "max": 1
        }
      ]
    },
    {
      "chance": 1.0,
      "outOf": 17500.0,
      "dropOne": false,
      "drops": [
        {
          "id": 5294,
          "min": 1,
          "max": 1
        }
      ]
    },
    {
      "chance": 1.0,
      "outOf": 17500.0,
      "dropOne": false,
      "drops": [
        {
          "id": 5295,
          "min": 1,
          "max": 1
        }
      ]
    },
    {
      "chance": 1.0,
      "outOf": 17500.0,
      "dropOne": false,
      "drops": [
        {
          "id": 5296,
          "min": 1,
          "max": 1
        }
      ]
    },
    {
      "chance": 1.0,
      "outOf": 17500.0,
      "dropOne": false,
      "drops": [
        {
          "id": 5297,
          "min": 1,
          "max": 1
        }
      ]
    },
    {
      "chance": 1.0,
      "outOf": 17500.0,
      "dropOne": false,
      "drops": [
        {
          "id": 5298,
          "min": 1,
          "max": 1
        }
      ]
    },
    {
      "chance": 1.0,
      "outOf": 17500.0,
      "dropOne": false,
      "drops": [
        {
          "id": 5299,
          "min": 1,
          "max": 1
        }
      ]
    },
    {
      "chance": 1.0,
      "outOf": 17500.0,
      "dropOne": false,
      "drops": [
        {
          "id": 5300,
          "min": 1,
          "max": 1
        }
      ]
    },
    {
      "chance": 1.0,
      "outOf": 17500.0,
      "dropOne": false,
      "drops": [
        {
          "id": 5301,
          "min": 1,
          "max": 1
        }
      ]
    },
    {
      "chance": 1.0,
      "outOf": 17500.0,
      "dropOne": false,
      "drops": [
        {
          "id": 5302,
          "min": 1,
          "max": 1
        }
      ]
    },
    {
      "chance": 1.0,
      "outOf": 17500.0,
      "dropOne": false,
      "drops": [
        {
          "id": 5303,
          "min": 1,
          "max": 1
        }
      ]
    },
    {
      "chance": 1.0,
      "outOf": 17500.0,
      "dropOne": false,
      "drops": [
        {
          "id": 5304,
          "min": 1,
          "max": 1
        }
      ]
    },
    {
      "chance": 1.0,
      "outOf": 17500.0,
      "dropOne": false,
      "drops": [
        {
          "id": 5311,
          "min": 1,
          "max": 1
        }
      ]
    },
    {
      "chance": 1.0,
      "outOf": 17500.0,
      "dropOne": false,
      "drops": [
        {
          "id": 5321,
          "min": 1,
          "max": 1
        }
      ]
    },
    {
      "chance": 1.0,
      "outOf": 17500.0,
      "dropOne": false,
      "drops": [
        {
          "id": 5323,
          "min": 1,
          "max": 1
        }
      ]
    },
    {
      "chance": 1.0,
      "outOf": 17500.0,
      "dropOne": false,
      "drops": [
        {
          "id": 12176,
          "min": 1,
          "max": 1
        }
      ]
    }
  ]
}