{
  "name": "Aleck's Hunter Emporium",
  "generalStore": false,
  "buyOnly": false,
  "currency": 995,
  "items": [
    {
      "item": {
        "id": 10006,
        "amount": 30
      }
    },
    {
      "item": {
        "id": 10008,
        "amount": 30
      }
    },
    {
      "item": {
        "id": 10012,
        "amount": 300
      }
    },
    {
      "item": {
        "id": 10010,
        "amount": 10
      }
    },
    {
      "item": {
        "id": 10025,
        "amount": 300
      }
    },
    {
      "item": {
        "id": 10029,
        "amount": 10
      }
    },
    {
      "item": {
        "id": 10031,
        "amount": 30
      }
    },
    {
      "item": {
        "id": 10150,
        "amount": 10
      }
    },
    {
      "item": {
        "id": 12539,
        "amount": 0
      }
    }
  ],
  "npcIds": [
    5111,
    14864
  ]
}