{
  "names": [
    "TokHaar-Jad"
  ],
  "attackAnim": 16204,
  "attackSound": -1,
  "defenceAnim": 16201,
  "defendSound": -1,
  "deathAnim": 16188,
  "deathDelay": 12,
  "deathSound": -1,
  "respawnDelay": 0,
  "hitpoints": 2500,
  "maxHit": 1014,
  "attackStyle": "RANGE",
  "combatLevels": {
    "ATTACK": 2000,
    "RANGE": 2000,
    "STRENGTH": 1000,
    "DEFENSE": 1000,
    "MAGE": 800
  },
  "attackRange": 10,
  "attackGfx": -1,
  "attackProjectile": -1,
  "agressivenessType": "AGGRESSIVE",
  "aggroDistance": 64,
  "deAggroDistance": -1,
  "maxDistFromSpawn": -1
}